Classfile /E:/dsz-git-work/jvm/src/main/java/com/dsz/jvm/test1/Test2.class
  Last modified 2021Äê10ÔÂ20ÈÕ; size 731 bytes
  MD5 checksum a2dce67916aee23ff7fc14423bb4d93e
  Compiled from "Test2.java"
public class com.dsz.jvm.test1.Test2
  minor version: 0
  major version: 55
  flags: (0x0021) ACC_PUBLIC, ACC_SUPER
  this_class: #7                          // com/dsz/jvm/test1/Test2
  super_class: #12                        // java/lang/Object
  interfaces: 0, fields: 5, methods: 3, attributes: 1
Constant pool:
   #1 = Methodref          #12.#32        // java/lang/Object."<init>":()V
   #2 = String             #33            // msg666
   #3 = Fieldref           #7.#34         // com/dsz/jvm/test1/Test2.msg:Ljava/lang/String;
   #4 = Fieldref           #35.#36        // java/lang/System.out:Ljava/io/PrintStream;
   #5 = Fieldref           #7.#37         // com/dsz/jvm/test1/Test2.i:I
   #6 = Methodref          #38.#39        // java/io/PrintStream.println:(I)V
   #7 = Class              #40            // com/dsz/jvm/test1/Test2
   #8 = Methodref          #7.#32         // com/dsz/jvm/test1/Test2."<init>":()V
   #9 = Fieldref           #7.#41         // com/dsz/jvm/test1/Test2.test2:Lcom/dsz/jvm/test1/Test2;
  #10 = String             #42            // staticMsg666
  #11 = Fieldref           #7.#43         // com/dsz/jvm/test1/Test2.staticMsg:Ljava/lang/String;
  #12 = Class              #44            // java/lang/Object
  #13 = Utf8               name
  #14 = Utf8               Ljava/lang/String;
  #15 = Utf8               ConstantValue
  #16 = String             #45            // my name
  #17 = Utf8               test2
  #18 = Utf8               Lcom/dsz/jvm/test1/Test2;
  #19 = Utf8               i
  #20 = Utf8               I
  #21 = Utf8               msg
  #22 = Utf8               staticMsg
  #23 = Utf8               <init>
  #24 = Utf8               ()V
  #25 = Utf8               Code
  #26 = Utf8               LineNumberTable
  #27 = Utf8               main
  #28 = Utf8               ([Ljava/lang/String;)V
  #29 = Utf8               <clinit>
  #30 = Utf8               SourceFile
  #31 = Utf8               Test2.java
  #32 = NameAndType        #23:#24        // "<init>":()V
  #33 = Utf8               msg666
  #34 = NameAndType        #21:#14        // msg:Ljava/lang/String;
  #35 = Class              #46            // java/lang/System
  #36 = NameAndType        #47:#48        // out:Ljava/io/PrintStream;
  #37 = NameAndType        #19:#20        // i:I
  #38 = Class              #49            // java/io/PrintStream
  #39 = NameAndType        #50:#51        // println:(I)V
  #40 = Utf8               com/dsz/jvm/test1/Test2
  #41 = NameAndType        #17:#18        // test2:Lcom/dsz/jvm/test1/Test2;
  #42 = Utf8               staticMsg666
  #43 = NameAndType        #22:#14        // staticMsg:Ljava/lang/String;
  #44 = Utf8               java/lang/Object
  #45 = Utf8               my name
  #46 = Utf8               java/lang/System
  #47 = Utf8               out
  #48 = Utf8               Ljava/io/PrintStream;
  #49 = Utf8               java/io/PrintStream
  #50 = Utf8               println
  #51 = Utf8               (I)V
{
  private static final java.lang.String name;
    descriptor: Ljava/lang/String;
    flags: (0x001a) ACC_PRIVATE, ACC_STATIC, ACC_FINAL
    ConstantValue: String my name

  private static final com.dsz.jvm.test1.Test2 test2;
    descriptor: Lcom/dsz/jvm/test1/Test2;
    flags: (0x001a) ACC_PRIVATE, ACC_STATIC, ACC_FINAL

  private static int i;
    descriptor: I
    flags: (0x000a) ACC_PRIVATE, ACC_STATIC

  private java.lang.String msg;
    descriptor: Ljava/lang/String;
    flags: (0x0002) ACC_PRIVATE

  private static java.lang.String staticMsg;
    descriptor: Ljava/lang/String;
    flags: (0x000a) ACC_PRIVATE, ACC_STATIC

  public com.dsz.jvm.test1.Test2();
    descriptor: ()V
    flags: (0x0001) ACC_PUBLIC
    Code:
      stack=2, locals=1, args_size=1
         0: aload_0
         1: invokespecial #1                  // Method java/lang/Object."<init>":()V
         4: aload_0
         5: ldc           #2                  // String msg666
         7: putfield      #3                  // Field msg:Ljava/lang/String;
        10: return
      LineNumberTable:
        line 7: 0
        line 16: 4

  public static void main(java.lang.String[]);
    descriptor: ([Ljava/lang/String;)V
    flags: (0x0009) ACC_PUBLIC, ACC_STATIC
    Code:
      stack=2, locals=1, args_size=1
         0: getstatic     #4                  // Field java/lang/System.out:Ljava/io/PrintStream;
         3: getstatic     #5                  // Field i:I
         6: invokevirtual #6                  // Method java/io/PrintStream.println:(I)V
         9: return
      LineNumberTable:
        line 31: 0
        line 32: 9

  static {};
    descriptor: ()V
    flags: (0x0008) ACC_STATIC
    Code:
      stack=2, locals=0, args_size=0
         0: new           #7                  // class com/dsz/jvm/test1/Test2
         3: dup
         4: invokespecial #8                  // Method "<init>":()V
         7: putstatic     #9                  // Field test2:Lcom/dsz/jvm/test1/Test2;
        10: sipush        666
        13: putstatic     #5                  // Field i:I
        16: ldc           #10                 // String staticMsg666
        18: putstatic     #11                 // Field staticMsg:Ljava/lang/String;
        21: return
      LineNumberTable:
        line 12: 0
        line 14: 10
        line 20: 16
}
SourceFile: "Test2.java"
